<?xml version="1.0" encoding="UTF-8" ?>  
<!DOCTYPE mapper  
  PUBLIC "-//mybatis.org//DTD Mapper 3.0//EN"   
  "http://mybatis.org/dtd/mybatis-3-mapper.dtd">  
<mapper namespace="com.galaxy.im.bean.operationLog.OperationLogs">

	<!-- 保存 -->
	<insert id="saveOperationLog" useGeneratedKeys="true" keyProperty="id"  keyColumn="id" parameterType="com.galaxy.im.bean.operationLog.OperationLogs" >
	    insert into sop_operation_logs (uid, uname, 
	      user_roleId, user_role, user_departId, 
	      depart_name, operation_type, project_id, 
	      project_name, sop_stage, operation_content, created_time,record_type,record_id,reason
	      )
	    values (#{uid}, #{uname}, #{userRoleid}, #{userRole}, #{userDepartid}, 
	      #{departName}, #{operationType}, #{projectId}, #{projectName}, #{sopstage},
	      #{operationContent},#{createdTime},#{recordType},#{recordId}, #{reason}
	      )
	    <selectKey resultType="java.lang.Long" order="AFTER" keyProperty="id">
			SELECT LAST_INSERT_ID() AS id
		</selectKey>
    </insert>
    
    <!-- 操作日志列表 -->
	<select id="getOperationLogList" parameterType="hashmap" resultType="hashmap">
		SELECT 
			uid uId,
			uname uName,
			operation_content operationContent,
			date_format(from_unixtime(created_time/1000),'%Y/%m/%d') createdTime, 
			reason
		FROM sop_operation_logs 
		WHERE record_type=4 and uid=#{uid} and record_id=#{recordId}
		ORDER BY created_time DESC
		LIMIT #{offset},${limit};
	</select>
	
	<!-- 操作日志列表个数 -->
	<select id="countOperationLogList" parameterType="hashmap" resultType="integer">
		SELECT count(1) 
		FROM sop_operation_logs 
		WHERE record_type=4 and uid=#{uid} and record_id=#{recordId}
		ORDER BY created_time DESC
	</select>
    
</mapper>